agregator_mess-0.0.1.dist-info/LICENSE.txt
agregator_mess-0.0.1.dist-info/METADATA
agregator_mess-0.0.1.dist-info/RECORD
agregator_mess-0.0.1.dist-info/WHEEL
agregator_mess-0.0.1.dist-info/entry_points.txt
agregator_mess-0.0.1.dist-info/top_level.txt
core/Manager.py
core/UIInit.py
core/__init__.py
core/MessengerAPI/Authorization.py
core/MessengerAPI/MessengerAPI.py
core/MessengerAPI/TelegramApi.py
core/MessengerAPI/VKApi.py
core/MessengerAPI/__init__.py
