Metadata-Version: 2.1
Name: agregator-mess
Version: 0.0.1
Summary: University project.
Home-page: https://github.com/moevm/gui-1h2018-28
Author: MOEVM
License: UNKNOWN
Keywords: vk telegram university messenger
Platform: UNKNOWN
Classifier: Development Status :: 3 - Alpha
Classifier: License :: OSI Approved :: MIT License
Classifier: Programming Language :: Python :: 3.3
Classifier: Programming Language :: Python :: 3.4
Classifier: Programming Language :: Python :: 3.5
Classifier: Programming Language :: Python :: 3.6
Requires-Dist: vk-api
Requires-Dist: PyQt5
Requires-Dist: telethon
